scripts/__init__.py
scripts/meural_cli.py
scripts/meural_mcp.py
meural/__init__.py
meural/api.py
meural/auth.py
meural-0.1.0.dist-info/METADATA
meural-0.1.0.dist-info/WHEEL
meural-0.1.0.dist-info/entry_points.txt
meural-0.1.0.dist-info/RECORD
