Metadata-Version: 2.4
Name: meural
Version: 0.1.0
Summary: Python client library and MCP server for Meural Canvas digital art frames
Project-URL: Homepage, https://github.com/mikelambert/meural_api
Project-URL: Repository, https://github.com/mikelambert/meural_api
Project-URL: Issues, https://github.com/mikelambert/meural_api/issues
Author-email: Mike Lambert <mlambert@gmail.com>
License: MIT
Keywords: api,digital-art,mcp,meural,smart-home
Classifier: Development Status :: 4 - Beta
Classifier: Intended Audience :: Developers
Classifier: License :: OSI Approved :: MIT License
Classifier: Programming Language :: Python :: 3
Classifier: Programming Language :: Python :: 3.10
Classifier: Programming Language :: Python :: 3.11
Classifier: Programming Language :: Python :: 3.12
Classifier: Programming Language :: Python :: 3.13
Classifier: Topic :: Home Automation
Requires-Python: >=3.10
Requires-Dist: pycognito>=2024.5.1
Requires-Dist: requests>=2.28.0
Provides-Extra: all
Requires-Dist: click>=8.0.0; extra == 'all'
Requires-Dist: mcp>=1.0.0; extra == 'all'
Requires-Dist: pytest>=7.0.0; extra == 'all'
Requires-Dist: tabulate>=0.9.0; extra == 'all'
Provides-Extra: cli
Requires-Dist: click>=8.0.0; extra == 'cli'
Requires-Dist: tabulate>=0.9.0; extra == 'cli'
Provides-Extra: dev
Requires-Dist: pytest>=7.0.0; extra == 'dev'
Provides-Extra: mcp
Requires-Dist: mcp>=1.0.0; extra == 'mcp'
